[
 {
  "question": "  It is bad to take\u2026\u2026\u2026\u2026 property without permission. ",
  "option": {
   "a": "someone else's ",
   "b": "someone\u2019s else",
   "c": " someone's ",
   "d": "someone's else's' "
  },
  "section": "most appropriate option",
  "image": "",
  "answer": "b",
  "solution": "",
  "examtype": "utme",
  "examyear": "2003"
 },
 {
  "question": "It is often\u2026\u2026. that inflation \u2026\u2026\u2026.  from too much money chasing very few goods.    ",
  "option": {
   "a": "said/results",
   "b": "say/result      ",
   "c": "said/result   ",
   "d": "say/ resulted"
  },
  "section": "most appropriate option",
  "image": "",
  "answer": "a",
  "solution": "",
  "examtype": "utme",
  "examyear": "2003"
 },
 {
  "question": "The sergeant spoke to me in a \u2026\u2026\u2026\u2026\u2026  manner",
  "option": {
   "a": "Coarse",
   "b": "causal     ",
   "c": "coerce    ",
   "d": "course "
  },
  "section": "most appropriate option",
  "image": "",
  "answer": "a",
  "solution": "",
  "examtype": "utme",
  "examyear": "2003"
 },
 {
  "question": "Only those who are <i>gullible</i> fall victim to his trickery ",
  "option": {
   "a": "astute ",
   "b": "Courteous ",
   "c": "saucy ",
   "d": "devastated"
  },
  "section": "opposite in meaning to the word(s) or phrase in italics ",
  "image": "",
  "answer": "a",
  "solution": "",
  "examtype": "utme",
  "examyear": "2003"
 },
 {
  "question": "The witness decided to <i>conceal</i> the evidence ",
  "option": {
   "a": "waive ",
   "b": "divulge ",
   "c": "hide",
   "d": "destroy "
  },
  "section": "opposite in meaning to the word(s) or phrase in italics ",
  "image": "",
  "answer": "b",
  "solution": "",
  "examtype": "utme",
  "examyear": "2003"
 },
 {
  "question": "He is well known for his <i>inordinate</i> ambition ",
  "option": {
   "a": "passionate ",
   "b": "sound ",
   "c": "excessive",
   "d": "moderate "
  },
  "section": "opposite in meaning to the word(s) or phrase in italics ",
  "image": "",
  "answer": "d",
  "solution": "",
  "examtype": "utme",
  "examyear": "2003"
 },
 {
  "question": "The elders rebuked ",
  "option": {
   "a": "Olu for talking issue with his principal. ",
   "b": "Olu was scolded for acting in collusion with his principal ",
   "c": "Olu was reprimanded for arguing with his principal",
   "d": "Olu was blamed for issuing a statement denying his principal."
  },
  "section": "that best explains the information conveyed ",
  "image": "",
  "answer": "b",
  "solution": "",
  "examtype": "utme",
  "examyear": "2003"
 },
 {
  "question": "Adike \u2026\u2026\u2026\u2026.. a message from the club regularly.",
  "option": {
   "a": "Receive ",
   "b": " had received ",
   "c": " receive",
   "d": " has received "
  },
  "section": "most appropriate option",
  "image": "",
  "answer": "a",
  "solution": "",
  "examtype": "utme",
  "examyear": "2003"
 },
 {
  "question": "1 have the \u2026\u2026\u2026 of meeting the President.",
  "option": {
   "a": "privilege  ",
   "b": "privelege ",
   "c": "previlege ",
   "d": "privilege "
  },
  "section": "most appropriate option",
  "image": "",
  "answer": "d",
  "solution": "",
  "examtype": "utme",
  "examyear": "2003"
 },
 {
  "question": "Nowadays, many graduates are not Will disposed to teaching\u2026\u2026\u2026\u2026\u2026..",
  "option": {
   "a": "are they",
   "b": "aren't they?",
   "c": "do they?    ",
   "d": " they are?"
  },
  "section": "most appropriate option",
  "image": "",
  "answer": "a",
  "solution": "",
  "examtype": "utme",
  "examyear": "2003"
 },
 {
  "question": " It was a free-for-all and the students were blamed for taking the law",
  "option": {
   "a": "in their own hands ",
   "b": "into their own hands ",
   "c": "into their hands ",
   "d": "in their hands."
  },
  "section": "most appropriate option",
  "image": "",
  "answer": "b",
  "solution": "",
  "examtype": "utme",
  "examyear": "2003"
 },
 {
  "question": "The armed robbers went into the house and robbed the three",
  "option": {
   "a": "woman occupants",
   "b": "women's occupants ",
   "c": "woman's occupants",
   "d": "   women occupants."
  },
  "section": "most appropriate option",
  "image": "",
  "answer": "a",
  "solution": "",
  "examtype": "utme",
  "examyear": "2003"
 },
 {
  "question": "The doctor examined the patient <i>painstakingly</i> ",
  "option": {
   "a": "Carefully ",
   "b": "Perfunctorily ",
   "c": "Professionally ",
   "d": "Painfully "
  },
  "section": "opposite in meaning to the word(s) or phrase in italics ",
  "image": "",
  "answer": "c",
  "solution": "",
  "examtype": "utme",
  "examyear": "2003"
 },
 {
  "question": "Ali plays \u2026\u2026\u2026.violin with remarkable skill",
  "option": {
   "a": "a    ",
   "b": "the",
   "c": "their ",
   "d": "some "
  },
  "section": "most appropriate option",
  "image": "",
  "answer": "b",
  "solution": "",
  "examtype": "utme",
  "examyear": "2003"
 },
 {
  "question": "The company is to <i>shed</i> three thousand staff this year ",
  "option": {
   "a": "Throw up ",
   "b": "placate ",
   "c": "lay off",
   "d": "demote "
  },
  "section": "choose the option nearest in meaning to the word(s) or phrase in italics.",
  "image": "",
  "answer": "c",
  "solution": "",
  "examtype": "utme",
  "examyear": "2003"
 },
 {
  "question": "The members of the congregation were <i>inspired</i> by the sermon ",
  "option": {
   "a": "enthralled ",
   "b": "disenchanted ",
   "c": "disoriented ",
   "d": "bewitched "
  },
  "section": "opposite in meaning to the word(s) or phrase in italics ",
  "image": "",
  "answer": "b",
  "solution": "",
  "examtype": "utme",
  "examyear": "2003"
 },
 {
  "question": "c<u>olo</u>nel ",
  "option": {
   "a": " golden",
   "b": " girl",
   "c": " colony ",
   "d": " goal "
  },
  "section": "choose the option that has the same vowel sound as the one represented by the letter(s) underlined.",
  "image": "",
  "answer": "b",
  "solution": "",
  "examtype": "utme",
  "examyear": "2003"
 },
 {
  "question": "The <i>essence</i> of governance is to seek the good and well-being of the majority of the people ",
  "option": {
   "a": "characteristics ",
   "b": "importance ",
   "c": "Secret ",
   "d": "Goal"
  },
  "section": "choose the option nearest in meaning to the word(s) or phrase in italics.",
  "image": "",
  "answer": "b",
  "solution": "",
  "examtype": "utme",
  "examyear": "2003"
 },
 {
  "question": "Agbenu was <i>ecstatic</i> about her result ",
  "option": {
   "a": "sad",
   "b": "dispassionate ",
   "c": "mad ",
   "d": "pessimistic "
  },
  "section": "opposite in meaning to the word(s) or phrase in italics ",
  "image": "",
  "answer": "b",
  "solution": "",
  "examtype": "utme",
  "examyear": "2003"
 },
 {
  "question": "The nurse was in favour of <i>voluntary eutheanasia</i>",
  "option": {
   "a": "a sleeping pill",
   "b": "a major operation",
   "c": "a painless death",
   "d": "a simple operation"
  },
  "section": "choose the option nearest in meaning to the word(s) or phrase in italics.",
  "image": "",
  "answer": "c",
  "solution": "",
  "examtype": "utme",
  "examyear": "2003"
 },
 {
  "question": "The woman is one? of the \u2026\u2026\u2026\u2026. of the society.",
  "option": {
   "a": "elitist  ",
   "b": " elites ",
   "c": "ellte",
   "d": "elitists "
  },
  "section": "most appropriate option",
  "image": "",
  "answer": "c",
  "solution": "",
  "examtype": "utme",
  "examyear": "2003"
 },
 {
  "question": "",
  "option": {
   "a": "cost    ",
   "b": "won\u2019t    ",
   "c": "hope    ",
   "d": "coast "
  },
  "section": "choose the option that has a different vowel sound from the others.",
  "image": "",
  "answer": "a",
  "solution": "",
  "examtype": "utme",
  "examyear": "2003"
 },
 {
  "question": "The leader has the <i>unstinting</i> support of his party ",
  "option": {
   "a": "cautious ",
   "b": "uninspiring ",
   "c": "unsparing ",
   "d": "laudable "
  },
  "section": "choose the option nearest in meaning to the word(s) or phrase in italics.",
  "image": "",
  "answer": "c",
  "solution": "",
  "examtype": "utme",
  "examyear": "2003"
 },
 {
  "question": "If you saw the photograph of the man\u2026\u2026\u2026\u2026\u2026\u2026\u2026\u2026you be able to identify him?",
  "option": {
   "a": "could",
   "b": "would   ",
   "c": "can ",
   "d": "will "
  },
  "section": "most appropriate option",
  "image": "",
  "answer": "b",
  "solution": "",
  "examtype": "utme",
  "examyear": "2003"
 },
 {
  "question": "If you would do me this favour,  I \u2026\u2026\u2026\u2026..  be very grateful",
  "option": {
   "a": "should",
   "b": " would ",
   "c": " shall ",
   "d": "will"
  },
  "section": "most appropriate option",
  "image": "",
  "answer": "b",
  "solution": "",
  "examtype": "utme",
  "examyear": "2003"
 },
 {
  "question": "Typist",
  "option": {
   "a": "refuse  (noun)",
   "b": "superb",
   "c": "propose",
   "d": "rebel (verb)"
  },
  "section": "choose the option that has the same stress pattern as the given word.",
  "image": "",
  "answer": "a",
  "solution": "",
  "examtype": "utme",
  "examyear": "2003"
 },
 {
  "question": "The candidate's charisma should be a..\u2026\u2026\u2026factor in winning the election. ",
  "option": {
   "a": "determinant ",
   "b": "determinate",
   "c": "determining ",
   "d": "determinable "
  },
  "section": "most appropriate option",
  "image": "",
  "answer": "c",
  "solution": "",
  "examtype": "utme",
  "examyear": "2003"
 },
 {
  "question": "The carpenter built a <i>commodious</i> wardrobe ",
  "option": {
   "a": "wide ",
   "b": "gigantic ",
   "c": "small ",
   "d": "spacious"
  },
  "section": "choose the option nearest in meaning to the word(s) or phrase in italics.",
  "image": "",
  "answer": "d",
  "solution": "",
  "examtype": "utme",
  "examyear": "2003"
 },
 {
  "question": "I can't stand people prying into my private life. 'Ladi said '\u2026\u2026\u2026\u2026 agree Agbenu",
  "option": {
   "a": "Me too ",
   "b": "Likewise myself ",
   "c": "Me neither ",
   "d": "I also "
  },
  "section": "most appropriate option",
  "image": "",
  "answer": "b",
  "solution": "",
  "examtype": "utme",
  "examyear": "2003"
 },
 {
  "question": "",
  "option": {
   "a": "wife",
   "b": "of",
   "c": "off",
   "d": "laugh"
  },
  "section": "choose the option that has a different consonant sound from the others.",
  "image": "",
  "answer": "b",
  "solution": "",
  "examtype": "utme",
  "examyear": "2003"
 },
 {
  "question": "Toyin is married to an <i>impatient, self-centred man ",
  "option": {
   "a": "a tolerant ",
   "b": "a tolerable",
   "c": "a fretful ",
   "d": "an edgy"
  },
  "section": "opposite in meaning to the word(s) or phrase in italics ",
  "image": "",
  "answer": "a",
  "solution": "",
  "examtype": "utme",
  "examyear": "2003"
 },
 {
  "question": "If he went to London, he would see the Queen",
  "option": {
   "a": "He did not go to London and did not see the Queen",
   "b": " He would like to see the Queen when he goes to London",
   "c": "When he goes to London, he will see the Queen ",
   "d": "He did not see the queen when he went to London."
  },
  "section": "that best explains the information conveyed ",
  "image": "",
  "answer": "c",
  "solution": "",
  "examtype": "utme",
  "examyear": "2003"
 },
 {
  "question": "A cool bath in a hot weather can be truly <i>invigorating</i> ",
  "option": {
   "a": "debilitating ",
   "b": "devastating ",
   "c": "disgusting ",
   "d": "unpalatable"
  },
  "section": "opposite in meaning to the word(s) or phrase in italics ",
  "image": "",
  "answer": "a",
  "solution": "",
  "examtype": "utme",
  "examyear": "2003"
 },
 {
  "question": "Publishing as a business venture has become a <i>hot potato</i> in Nigeria. ",
  "option": {
   "a": "unacceptable  ",
   "b": "unpleasant ",
   "c": "expensive                                                              ",
   "d": "profitable"
  },
  "section": "choose the option nearest in meaning to the word(s) or phrase in italics.",
  "image": "",
  "answer": "b",
  "solution": "",
  "examtype": "utme",
  "examyear": "2003"
 },
 {
  "question": "",
  "option": {
   "a": "there   ",
   "b": "dear    ",
   "c": "fair         ",
   "d": "bear"
  },
  "section": "choose the option that has a different vowel sound from the others.",
  "image": "",
  "answer": "c",
  "solution": "",
  "examtype": "utme",
  "examyear": "2003"
 },
 {
  "question": "Classmate\u2026\u2026\u2026\u2026\u2026\u2026\u2026\u2026\u2026.  I haven't seen for years, wrote to me last week.",
  "option": {
   "a": "whose ",
   "b": "which ",
   "c": "that",
   "d": " whom"
  },
  "section": "most appropriate option",
  "image": "",
  "answer": "d",
  "solution": "",
  "examtype": "utme",
  "examyear": "2003"
 },
 {
  "question": "From what she said, one may <i>infer</i> that she does not like the course",
  "option": {
   "a": "agree ",
   "b": "deduce ",
   "c": "suppose ",
   "d": "realize "
  },
  "section": "choose the option nearest in meaning to the word(s) or phrase in italics.",
  "image": "",
  "answer": "b",
  "solution": "",
  "examtype": "utme",
  "examyear": "2003"
 },
 {
  "question": "A <i>conservative</i> estimate put the number of missing persons at forty.",
  "option": {
   "a": "an accurate ",
   "b": "An incorrect ",
   "c": "A rough ",
   "d": "Primitive "
  },
  "section": "opposite in meaning to the word(s) or phrase in italics ",
  "image": "",
  "answer": "a",
  "solution": "",
  "examtype": "utme",
  "examyear": "2003"
 },
 {
  "question": "The reason why he was not offered admission was \u2026\u2026\u2026\u2026\u2026 his results could not be found.",
  "option": {
   "a": "that   ",
   "b": "when  ",
   "c": "owing to ",
   "d": "because "
  },
  "section": "most appropriate option",
  "image": "",
  "answer": "a",
  "solution": "",
  "examtype": "utme",
  "examyear": "2003"
 },
 {
  "question": "The agency has sworn to deal  with all the <i>apostles</i>  of confederation ",
  "option": {
   "a": "opponents ",
   "b": "apostates ",
   "c": "Proponents ",
   "d": "Protagonists "
  },
  "section": "opposite in meaning to the word(s) or phrase in italics ",
  "image": "",
  "answer": "a",
  "solution": "",
  "examtype": "utme",
  "examyear": "2003"
 }
]